mpc_orb/README.md
mpc_orb/__init__.py
mpc_orb/interpret.py
mpc_orb/parse.py
mpc_orb/validate_mpcorb.py
mpc_orb/bin/demo.py
mpc_orb/demo_json/2012HN13_mpcorb_yarkovsky.json
mpc_orb/demo_json/2020AB_mpcorb.json
mpc_orb/schema_json/README.md
mpc_orb/schema_json/mpcorb_schema_v0.1.json
mpc_orb/schema_json/mpcorb_schema_v0.2.json
mpc_orb/schema_json/mpcorb_schema_v0.3.json
mpc_orb/schema_json/mpcorb_schema_v0.4.json
mpc_orb/schema_json/mpcorb_schema_v0.5.json
mpc_orb/schema_json/mpcorb_schema_vlatest.json
mpc_orb-0.2.1.dist-info/METADATA
mpc_orb-0.2.1.dist-info/WHEEL
mpc_orb-0.2.1.dist-info/entry_points.txt
mpc_orb-0.2.1.dist-info/licenses/LICENSE
mpc_orb-0.2.1.dist-info/RECORD
